scope_timer/__init__.py
scope_timer/core.py
scope_timer/infer.py
scope_timer/node.py
scope_timer/record.py
scope_timer/stats.py
scope_timer/thread_local.py
scope_timer/version.py
scope_timer-0.3.0.dist-info/METADATA
scope_timer-0.3.0.dist-info/WHEEL
scope_timer-0.3.0.dist-info/licenses/LICENSE
scope_timer-0.3.0.dist-info/RECORD
