Metadata-Version: 2.4
Name: scope-timer
Version: 0.3.0
Summary: Lightweight scope-based Python profiler with colorful, hierarchical execution time reports.
Project-URL: Homepage, https://github.com/skst328/scope-timer
Project-URL: Bug Tracker, https://github.com/skst328/scope-timer/issues
Author: skst328
License: MIT License
License-File: LICENSE
Keywords: performance,profiler,rich,scope,timer,timing
Classifier: Development Status :: 4 - Beta
Classifier: Intended Audience :: Developers
Classifier: License :: OSI Approved :: MIT License
Classifier: Operating System :: OS Independent
Classifier: Programming Language :: Python :: 3
Classifier: Programming Language :: Python :: 3.10
Classifier: Programming Language :: Python :: 3.11
Classifier: Programming Language :: Python :: 3.12
Classifier: Topic :: Software Development :: Libraries :: Python Modules
Classifier: Topic :: System :: Benchmark
Requires-Python: >=3.10
Requires-Dist: rich>=13.0.0
Provides-Extra: test
Requires-Dist: pytest-cov>=6.0.0; extra == 'test'
Requires-Dist: pytest>=8.0.0; extra == 'test'
